spirv_enums/__init__.py
spirv_enums-1.0.dist-info/LICENSE
spirv_enums-1.0.dist-info/WHEEL
spirv_enums-1.0.dist-info/METADATA
spirv_enums-1.0.dist-info/RECORD
